causalflows/__init__.py
causalflows/conftest.py
causalflows/core.py
causalflows/distributions.py
causalflows/flows.py
causalflows/scms.py
causalflows-0.1.0.dist-info/LICENSE
causalflows-0.1.0.dist-info/METADATA
causalflows-0.1.0.dist-info/WHEEL
causalflows-0.1.0.dist-info/top_level.txt
causalflows-0.1.0.dist-info/RECORD
