Metadata-Version: 2.2
Name: causalflows
Version: 0.1.0
Summary: Causal Normalizing flows in PyTorch
Author-email: Adrián Javaloy <ajavaloy@ed.ac.uk>
Project-URL: documentation, https://causal-flows.readthedocs.io/
Project-URL: source, https://github.com/adrianjav/causal-flows
Project-URL: tracker, https://github.com/adrianjav/causal-flows/issues
Keywords: torch,normalizing flows,probability,distribution,generative,deep learning,causal inference
Classifier: Intended Audience :: Developers
Classifier: Intended Audience :: Science/Research
Classifier: License :: OSI Approved :: MIT License
Classifier: Natural Language :: English
Classifier: Operating System :: OS Independent
Classifier: Programming Language :: Python :: 3
Requires-Python: >=3.10
License-File: LICENSE
Requires-Dist: zuko>=1.3.1
Provides-Extra: dev
Requires-Dist: pre-commit; extra == "dev"
Requires-Dist: pytest; extra == "dev"
Requires-Dist: ruff; extra == "dev"
